[
  {
    "id": 1,
    "name": "Wagah Border",
    "country_from": "India",
    "country_to": "Pakistan",
    "lat": 31.6040,
    "lng": 74.5726,
    "status": "Active",
    "crossings_per_day": 1200,
    "wait_time_minutes": 45,
    "type": "Land",
    "risk_level": "High",
    "commodity": "Textiles"
  },
  {
    "id": 2,
    "name": "Petrapole-Benapole",
    "country_from": "India",
    "country_to": "Bangladesh",
    "lat": 23.0167,
    "lng": 88.9333,
    "status": "Active",
    "crossings_per_day": 3500,
    "wait_time_minutes": 30,
    "type": "Land",
    "risk_level": "Low",
    "commodity": "Agriculture"
  },
  {
    "id": 3,
    "name": "Attari-Lahore",
    "country_from": "India",
    "country_to": "Pakistan",
    "lat": 31.7167,
    "lng": 74.8667,
    "status": "Restricted",
    "crossings_per_day": 500,
    "wait_time_minutes": 90,
    "type": "Land",
    "risk_level": "High",
    "commodity": "Textiles"
  },
  {
    "id": 4,
    "name": "Moreh-Tamu",
    "country_from": "India",
    "country_to": "Myanmar",
    "lat": 24.2500,
    "lng": 94.2667,
    "status": "Active",
    "crossings_per_day": 800,
    "wait_time_minutes": 20,
    "type": "Land",
    "risk_level": "Medium",
    "commodity": "Electronics"
  },
  {
    "id": 5,
    "name": "Nathu La Pass",
    "country_from": "India",
    "country_to": "China",
    "lat": 27.3833,
    "lng": 88.8333,
    "status": "Seasonal",
    "crossings_per_day": 200,
    "wait_time_minutes": 60,
    "type": "Mountain Pass",
    "risk_level": "Medium",
    "commodity": "Minerals"
  },
  {
    "id": 6,
    "name": "Calais-Dover",
    "country_from": "France",
    "country_to": "United Kingdom",
    "lat": 50.9513,
    "lng": 1.8587,
    "status": "Active",
    "crossings_per_day": 10000,
    "wait_time_minutes": 15,
    "type": "Sea/Tunnel",
    "risk_level": "Low",
    "commodity": "Automobiles"
  },
  {
    "id": 7,
    "name": "US-Mexico San Ysidro",
    "country_from": "United States",
    "country_to": "Mexico",
    "lat": 32.5500,
    "lng": -117.0333,
    "status": "Active",
    "crossings_per_day": 75000,
    "wait_time_minutes": 35,
    "type": "Land",
    "risk_level": "Medium",
    "commodity": "Automobiles"
  },
  {
    "id": 8,
    "name": "US-Canada Peace Arch",
    "country_from": "United States",
    "country_to": "Canada",
    "lat": 48.9988,
    "lng": -122.7558,
    "status": "Active",
    "crossings_per_day": 25000,
    "wait_time_minutes": 10,
    "type": "Land",
    "risk_level": "Low",
    "commodity": "Energy"
  },
  {
    "id": 9,
    "name": "Rafah Crossing",
    "country_from": "Egypt",
    "country_to": "Palestine",
    "lat": 31.2833,
    "lng": 34.2333,
    "status": "Restricted",
    "crossings_per_day": 100,
    "wait_time_minutes": 180,
    "type": "Land",
    "risk_level": "High",
    "commodity": "Humanitarian Aid"
  },
  {
    "id": 10,
    "name": "Bab al-Hawa",
    "country_from": "Turkey",
    "country_to": "Syria",
    "lat": 36.2833,
    "lng": 36.6333,
    "status": "Restricted",
    "crossings_per_day": 300,
    "wait_time_minutes": 120,
    "type": "Land",
    "risk_level": "High",
    "commodity": "Humanitarian Aid"
  },
  {
    "id": 11,
    "name": "Singapore-Malaysia Woodlands",
    "country_from": "Singapore",
    "country_to": "Malaysia",
    "lat": 1.4433,
    "lng": 103.7767,
    "status": "Active",
    "crossings_per_day": 50000,
    "wait_time_minutes": 20,
    "type": "Land/Bridge",
    "risk_level": "Low",
    "commodity": "Electronics"
  },
  {
    "id": 12,
    "name": "Hong Kong-China Lo Wu",
    "country_from": "Hong Kong",
    "country_to": "China",
    "lat": 22.5267,
    "lng": 114.1133,
    "status": "Active",
    "crossings_per_day": 80000,
    "wait_time_minutes": 25,
    "type": "Rail/Land",
    "risk_level": "Low",
    "commodity": "Electronics"
  },
  {
    "id": 13,
    "name": "Beitbridge",
    "country_from": "South Africa",
    "country_to": "Zimbabwe",
    "lat": -22.2167,
    "lng": 29.9833,
    "status": "Active",
    "crossings_per_day": 8000,
    "wait_time_minutes": 240,
    "type": "Land/Bridge",
    "risk_level": "High",
    "commodity": "Mining"
  },
  {
    "id": 14,
    "name": "Chirundu",
    "country_from": "Zambia",
    "country_to": "Zimbabwe",
    "lat": -16.0333,
    "lng": 28.8833,
    "status": "Active",
    "crossings_per_day": 4500,
    "wait_time_minutes": 180,
    "type": "Land/Bridge",
    "risk_level": "High",
    "commodity": "Agriculture"
  },
  {
    "id": 15,
    "name": "Nimule-Elegu",
    "country_from": "South Sudan",
    "country_to": "Uganda",
    "lat": 3.6000,
    "lng": 32.0667,
    "status": "Active",
    "crossings_per_day": 2000,
    "wait_time_minutes": 90,
    "type": "Land",
    "risk_level": "High",
    "commodity": "Agriculture"
  },
  {
    "id": 16,
    "name": "Foz do Iguacu-Ciudad del Este",
    "country_from": "Brazil",
    "country_to": "Paraguay",
    "lat": -25.5167,
    "lng": -54.5833,
    "status": "Active",
    "crossings_per_day": 30000,
    "wait_time_minutes": 40,
    "type": "Land/Bridge",
    "risk_level": "Medium",
    "commodity": "Electronics"
  },
  {
    "id": 17,
    "name": "Desaguadero",
    "country_from": "Peru",
    "country_to": "Bolivia",
    "lat": -16.5667,
    "lng": -69.0333,
    "status": "Active",
    "crossings_per_day": 5000,
    "wait_time_minutes": 55,
    "type": "Land",
    "risk_level": "Medium",
    "commodity": "Minerals"
  },
  {
    "id": 18,
    "name": "Paso Los Libertadores",
    "country_from": "Argentina",
    "country_to": "Chile",
    "lat": -32.8333,
    "lng": -70.1167,
    "status": "Seasonal",
    "crossings_per_day": 6000,
    "wait_time_minutes": 50,
    "type": "Mountain Pass",
    "risk_level": "Medium",
    "commodity": "Agriculture"
  },
  {
    "id": 19,
    "name": "Choucha-Ras Jdir",
    "country_from": "Tunisia",
    "country_to": "Libya",
    "lat": 33.1667,
    "lng": 11.5333,
    "status": "Restricted",
    "crossings_per_day": 1500,
    "wait_time_minutes": 150,
    "type": "Land",
    "risk_level": "High",
    "commodity": "Energy"
  },
  {
    "id": 20,
    "name": "Noi Bai-Friendship Pass",
    "country_from": "Vietnam",
    "country_to": "China",
    "lat": 22.8000,
    "lng": 106.7167,
    "status": "Active",
    "crossings_per_day": 7000,
    "wait_time_minutes": 35,
    "type": "Land",
    "risk_level": "Low",
    "commodity": "Electronics"
  },
  {
    "id": 21,
    "name": "Aranyaprathet-Poipet",
    "country_from": "Thailand",
    "country_to": "Cambodia",
    "lat": 13.6833,
    "lng": 102.5500,
    "status": "Active",
    "crossings_per_day": 12000,
    "wait_time_minutes": 25,
    "type": "Land",
    "risk_level": "Low",
    "commodity": "Agriculture"
  },
  {
    "id": 22,
    "name": "Kyakhta-Altanbulag",
    "country_from": "Russia",
    "country_to": "Mongolia",
    "lat": 50.3667,
    "lng": 106.4500,
    "status": "Active",
    "crossings_per_day": 1800,
    "wait_time_minutes": 70,
    "type": "Land",
    "risk_level": "Medium",
    "commodity": "Minerals"
  },
  {
    "id": 23,
    "name": "Medyka-Shehyni",
    "country_from": "Poland",
    "country_to": "Ukraine",
    "lat": 49.8000,
    "lng": 22.9667,
    "status": "Active",
    "crossings_per_day": 15000,
    "wait_time_minutes": 80,
    "type": "Land",
    "risk_level": "High",
    "commodity": "Steel"
  },
  {
    "id": 24,
    "name": "Narva-Ivangorod",
    "country_from": "Estonia",
    "country_to": "Russia",
    "lat": 59.3667,
    "lng": 28.2000,
    "status": "Restricted",
    "crossings_per_day": 800,
    "wait_time_minutes": 120,
    "type": "Land/Bridge",
    "risk_level": "High",
    "commodity": "Energy"
  },
  {
    "id": 25,
    "name": "Laredo-Nuevo Laredo",
    "country_from": "United States",
    "country_to": "Mexico",
    "lat": 27.5036,
    "lng": -99.5075,
    "status": "Active",
    "crossings_per_day": 12400,
    "wait_time_minutes": 372,
    "type": "Land",
    "risk_level": "High",
    "commodity": "Automobiles"
  }
]